odoo10_addon_l10n_hr_bank-10.0.0.0.1-py2.7-nspkg.pth
odoo/addons/l10n_hr_bank/README.rst
odoo/addons/l10n_hr_bank/__init__.py
odoo/addons/l10n_hr_bank/__manifest__.py
odoo/addons/l10n_hr_bank/data/res_bank_data.xml
odoo/addons/l10n_hr_bank/i18n/en_US.po
odoo/addons/l10n_hr_bank/i18n/hr.po
odoo/addons/l10n_hr_bank/models/__init__.py
odoo/addons/l10n_hr_bank/models/res_partner_bank.py
odoo/addons/l10n_hr_bank/static/description/icon.png
odoo/addons/l10n_hr_bank/views/res_partner_bank_view.xml
odoo10_addon_l10n_hr_bank-10.0.0.0.1.dist-info/DESCRIPTION.rst
odoo10_addon_l10n_hr_bank-10.0.0.0.1.dist-info/METADATA
odoo10_addon_l10n_hr_bank-10.0.0.0.1.dist-info/RECORD
odoo10_addon_l10n_hr_bank-10.0.0.0.1.dist-info/WHEEL
odoo10_addon_l10n_hr_bank-10.0.0.0.1.dist-info/metadata.json
odoo10_addon_l10n_hr_bank-10.0.0.0.1.dist-info/namespace_packages.txt
odoo10_addon_l10n_hr_bank-10.0.0.0.1.dist-info/top_level.txt
