Metadata-Version: 2.0
Name: odoo10-addon-l10n-hr-bank
Version: 10.0.0.0.1
Summary: Croatia Banking localization
Home-page: https://github.com/OCA/l10n-croatia
Author: Odoo Community Association (OCA), Davor Bojkić (DAJ MI 5)
Author-email: support@odoo-community.org
License: AGPL-3
Platform: UNKNOWN
Classifier: Programming Language :: Python
Classifier: Framework :: Odoo
Classifier: License :: OSI Approved :: GNU Affero General Public License v3
Requires-Python: ~=2.7
Requires-Dist: odoo (<10.1dev,>=10.0)
